trg/__init__.py
trg/__main__.py
trg-2020.6.0.dist-info/AUTHORS.rst
trg-2020.6.0.dist-info/LICENSE
trg-2020.6.0.dist-info/METADATA
trg-2020.6.0.dist-info/WHEEL
trg-2020.6.0.dist-info/top_level.txt
trg-2020.6.0.dist-info/RECORD
